CHANGES.txt
MANIFEST.in
README.rst
setup.py
repoze/__init__.py
repoze.who.plugins.memcached.egg-info/PKG-INFO
repoze.who.plugins.memcached.egg-info/SOURCES.txt
repoze.who.plugins.memcached.egg-info/dependency_links.txt
repoze.who.plugins.memcached.egg-info/namespace_packages.txt
repoze.who.plugins.memcached.egg-info/not-zip-safe
repoze.who.plugins.memcached.egg-info/requires.txt
repoze.who.plugins.memcached.egg-info/top_level.txt
repoze/who/__init__.py
repoze/who/plugins/__init__.py
repoze/who/plugins/memcached/__init__.py
repoze/who/plugins/memcached/tests.py