Metadata-Version: 1.0
Name: repoze.who.plugins.memcached
Version: 0.1.1
Summary: repoze.who.plugins.memcached
Home-page: https://github.com/mozilla-services/repoze.who.plugins.memcached
Author: Mozilla Services
Author-email: services-dev@mozilla.org
License: UNKNOWN
Keywords: authentication repoze http memcache cache
Platform: UNKNOWN
Classifier: Programming Language :: Python
